cdk_cloudformation_datadog_monitors_monitor/__init__.py
cdk_cloudformation_datadog_monitors_monitor/py.typed
cdk_cloudformation_datadog_monitors_monitor/_jsii/__init__.py
cdk_cloudformation_datadog_monitors_monitor/_jsii/datadog-monitors-monitor@4.8.0-alpha.7.jsii.tgz
cdk_cloudformation_datadog_monitors_monitor-4.8.0a7.dist-info/LICENSE
cdk_cloudformation_datadog_monitors_monitor-4.8.0a7.dist-info/METADATA
cdk_cloudformation_datadog_monitors_monitor-4.8.0a7.dist-info/WHEEL
cdk_cloudformation_datadog_monitors_monitor-4.8.0a7.dist-info/top_level.txt
cdk_cloudformation_datadog_monitors_monitor-4.8.0a7.dist-info/RECORD
